LP_Examples/LPC_Class_Mix.py
LP_Examples/LPC_Class_Pride.py
LP_Examples/LPC_Method_1.py
LP_Examples/LPC_Method_Multiple.py
LP_Examples/LPC_NodeList_1.py
LP_Examples/__init__.py
LeetPride/Core.py
LeetPride/Examples.py
LeetPride/ListNode.py
LeetPride/TreeNode.py
LeetPride/__init__.py
docs/__init__.py
LeetPride-0.6.9.2.6.dist-info/License.txt
LeetPride-0.6.9.2.6.dist-info/METADATA
LeetPride-0.6.9.2.6.dist-info/WHEEL
LeetPride-0.6.9.2.6.dist-info/top_level.txt
LeetPride-0.6.9.2.6.dist-info/RECORD
