Metadata-Version: 2.1
Name: LeetPride
Version: 0.6.9.2.6
Summary: LeetPride makes for a beautiful problem solving and learning environment for test and timing data structures and algorithms. Happy Pride everyone and may the leet coding favor your fortune.
Home-page: https://github.com/Tallicia/LeetPride
Author: Alicia Yingling
Author-email: AliciaYingling@gmail.com
License: GNU AGPLv3
Platform: UNKNOWN
Classifier: Programming Language :: Python :: 3
Classifier: License :: OSI Approved :: GNU Affero General Public License v3
Classifier: Operating System :: OS Independent
Requires-Python: >=3.6
License-File: License.txt
Requires-Dist: colorama
Requires-Dist: pystyle
